README.rst
setup.py
src/hypothesis_fakefactory.egg-info/PKG-INFO
src/hypothesis_fakefactory.egg-info/SOURCES.txt
src/hypothesis_fakefactory.egg-info/dependency_links.txt
src/hypothesis_fakefactory.egg-info/requires.txt
src/hypothesis_fakefactory.egg-info/top_level.txt
src/hypothesisfakefactory/__init__.py